git_conventional_version/__init__.py
git_conventional_version/api.py
git_conventional_version/cli.py
git_conventional_version/changelog/__init__.py
git_conventional_version/changelog/changelog.py
git_conventional_version/versioning/__init__.py
git_conventional_version/versioning/conventional.py
git_conventional_version/versioning/releases.py
git_conventional_version/versioning/versions.py
git_conventional_version-1.0.2.dist-info/LICENSE
git_conventional_version-1.0.2.dist-info/METADATA
git_conventional_version-1.0.2.dist-info/WHEEL
git_conventional_version-1.0.2.dist-info/entry_points.txt
git_conventional_version-1.0.2.dist-info/top_level.txt
git_conventional_version-1.0.2.dist-info/RECORD
