Metadata-Version: 2.1
Name: git-conventional-version
Version: 1.0.2
Summary: Automatic conventional version
Home-page: https://github.com/atudomain/git-conventional-version
Author: Adrian Tuzimek
Author-email: tuziomek@gmail.com
License: UNKNOWN
Project-URL: Bug Tracker, https://github.com/atudomain/git-conventional-version/issues
Platform: UNKNOWN
Classifier: Programming Language :: Python :: 3
Classifier: License :: OSI Approved :: MIT License
Classifier: Operating System :: OS Independent
Requires-Python: >=3.6
License-File: LICENSE
Requires-Dist: GitPython
